sinapsis_parakeet_tdt/__init__.py
sinapsis_parakeet_tdt/helpers/__init__.py
sinapsis_parakeet_tdt/helpers/tags.py
sinapsis_parakeet_tdt/templates/__init__.py
sinapsis_parakeet_tdt/templates/parakeet_tdt.py
sinapsis_parakeet_tdt-0.1.4.dist-info/licenses/LICENSE
sinapsis_parakeet_tdt-0.1.4.dist-info/METADATA
sinapsis_parakeet_tdt-0.1.4.dist-info/WHEEL
sinapsis_parakeet_tdt-0.1.4.dist-info/top_level.txt
sinapsis_parakeet_tdt-0.1.4.dist-info/RECORD
