Metadata-Version: 2.4
Name: sinapsis-parakeet-tdt
Version: 0.1.4
Summary: Speech to text using Parakeet TDT model
Author-email: SinapsisAI <dev@sinapsis.tech>
Project-URL: Homepage, https://sinapsis.tech
Project-URL: Documentation, https://docs.sinapsis.tech/docs
Project-URL: Tutorials, https://docs.sinapsis.tech/tutorials
Project-URL: Repository, https://github.com/Sinapsis-AI/sinapsis-speech.git
Requires-Python: >=3.10
License-File: LICENSE
Requires-Dist: cuda-python>=12.9.0
Requires-Dist: nemo-toolkit[asr]>=2.3.0
Requires-Dist: sinapsis>=0.2.3
Provides-Extra: data-tools
Requires-Dist: sinapsis-data-readers>=0.1.2; extra == "data-tools"
Provides-Extra: all
Requires-Dist: sinapsis-parakeet-tdt[data-tools]; extra == "all"
Dynamic: license-file
